pydynorrt-0.0.13.dist-info/top_level.txt
pydynorrt-0.0.13.dist-info/WHEEL
pydynorrt-0.0.13.dist-info/RECORD
pydynorrt-0.0.13.dist-info/LICENSE
pydynorrt-0.0.13.dist-info/METADATA
pydynorrt/pydynorrt.cpython-310-x86_64-linux-gnu.so
pydynorrt/pin_more.py
pydynorrt/__init__.py
pydynorrt/ballworld_2d.py
pydynorrt/libpin_col_manager.so
pydynorrt/test/test_cols.py
pydynorrt/test/__init__.py
pydynorrt/test/test_planners.py
pydynorrt/test/test_basic.py
pydynorrt/test/test_ik.py
pydynorrt/test/__pycache__/test_planners.cpython-312-pytest-8.2.0.pyc
pydynorrt/test/__pycache__/test_cols.cpython-312-pytest-8.2.0.pyc
pydynorrt/test/__pycache__/test_ik.cpython-312-pytest-8.2.0.pyc
pydynorrt/test/__pycache__/test_basic.cpython-312-pytest-8.2.0.pyc
pydynorrt/data/models/ur5_two_robots.srdf
pydynorrt/data/models/planar_quadrotor_column.srdf
pydynorrt/data/models/unicycle_parallel_park.urdf
pydynorrt/data/models/ur5_two_robots.urdf
pydynorrt/data/models/planar_quadrotor_column.urdf
pydynorrt/data/models/kuka.srdf
pydynorrt/data/models/se3_window.urdf
pydynorrt/data/models/ur5.srdf
pydynorrt/data/models/point_payload_two_robots.urdf
pydynorrt/data/models/point_payload_two_robots.srdf
pydynorrt/data/models/unicycle_bugtrap.srdf
pydynorrt/data/models/ur5_with_box.srdf
pydynorrt/data/models/iiwa.urdf
pydynorrt/data/models/se3_window.srdf
pydynorrt/data/models/unicycle_bugtrap.urdf
pydynorrt/data/models/unicycle_parallel_park.srdf
pydynorrt/data/models/ur5_robot.urdf
pydynorrt/data/models/ur5_robot_with_box.urdf
pydynorrt/data/models/meshes/kuka/iiwa_base.stl
pydynorrt/data/models/meshes/kuka/iiwa_link_4.stl
pydynorrt/data/models/meshes/kuka/kuka_to_sensor_mount.stl
pydynorrt/data/models/meshes/kuka/iiwa_link_1.stl
pydynorrt/data/models/meshes/kuka/case_shell.stl
pydynorrt/data/models/meshes/kuka/tennis_ball_smaller.obj
pydynorrt/data/models/meshes/kuka/assembled_ee.stl
pydynorrt/data/models/meshes/kuka/iiwa_link_6.stl
pydynorrt/data/models/meshes/kuka/iiwa_link_5.stl
pydynorrt/data/models/meshes/kuka/iiwa_link_3.stl
pydynorrt/data/models/meshes/kuka/sensor_to_case_mount.stl
